pyaiml21/__init__.py
pyaiml21/_version.py
pyaiml21/aiml.py
pyaiml21/chatbot.py
pyaiml21/exceptions.py
pyaiml21/kernel.py
pyaiml21/py.typed
pyaiml21/ast/__init__.py
pyaiml21/ast/category.py
pyaiml21/ast/node.py
pyaiml21/bot/__init__.py
pyaiml21/bot/_bot.py
pyaiml21/botconfig/__init__.py
pyaiml21/botconfig/config.py
pyaiml21/botconfig/misc.py
pyaiml21/botconfig/substitutions.py
pyaiml21/graphmaster/__init__.py
pyaiml21/graphmaster/graphmaster.py
pyaiml21/graphmaster/mongo_gm.py
pyaiml21/graphmaster/node.py
pyaiml21/graphmaster/pattern.py
pyaiml21/graphmaster/sqlite_gm.py
pyaiml21/graphmaster/stars.py
pyaiml21/interpreter/__init__.py
pyaiml21/interpreter/debugger.py
pyaiml21/interpreter/symbol_table.py
pyaiml21/interpreter/walker.py
pyaiml21/parser/__init__.py
pyaiml21/parser/_category_parser.py
pyaiml21/parser/_walker.py
pyaiml21/parser/_xml_lxml_parser.py
pyaiml21/parser/_xml_utils.py
pyaiml21/parser/logger.py
pyaiml21/parser/parser.py
pyaiml21/session/__init__.py
pyaiml21/session/bounded_list.py
pyaiml21/session/session.py
pyaiml21/stdlib/__init__.py
pyaiml21/stdlib/_pattern.py
pyaiml21/stdlib/maps.py
pyaiml21/stdlib/sets.py
pyaiml21/stdlib/_template/__init__.py
pyaiml21/stdlib/_template/_sraix.py
pyaiml21/stdlib/_template/_time.py
pyaiml21/utils/__init__.py
pyaiml21/utils/load_files.py
pyaiml21/utils/text_preprocessors.py
scripts/__init__.py
scripts/aiml.py
tests/__init__.py
tests/standard/__init__.py
tests/standard/test_bot_configuration.py
tests/unit_tests/__init__.py
tests/unit_tests/aiml.py
tests/unit_tests/ast/__init__.py
tests/unit_tests/ast/test_node.py
tests/unit_tests/botconfig/__init__.py
tests/unit_tests/botconfig/test_substitutions.py
tests/unit_tests/graphmaster/__init__.py
tests/unit_tests/graphmaster/test_path.py
tests/unit_tests/session/__init__.py
tests/unit_tests/session/test_bounded_list.py
tests/unit_tests/session/test_session.py
tests/unit_tests/stdlib/__init__.py
tests/unit_tests/stdlib/test_maps.py
tests/unit_tests/stdlib/test_sets.py
pyaiml21-1.0.1.post2.dist-info/LICENSE
pyaiml21-1.0.1.post2.dist-info/METADATA
pyaiml21-1.0.1.post2.dist-info/WHEEL
pyaiml21-1.0.1.post2.dist-info/entry_points.txt
pyaiml21-1.0.1.post2.dist-info/top_level.txt
pyaiml21-1.0.1.post2.dist-info/RECORD
