Metadata-Version: 2.1
Name: pyaiml21
Version: 1.0.1.post2
Summary: Simple interpreter for AIML 2.1
Home-page: https://gitlab.fi.muni.cz/nlp/pyaiml21
Author: Michal Barnišin
Author-email: xbarnis@fi.muni.cz
License: MIT
Keywords: aiml,interpreter,chatbots
Platform: unix
Platform: linux
Platform: osx
Platform: cygwin
Platform: win32
Classifier: Development Status :: 5 - Production/Stable
Classifier: Intended Audience :: Developers
Classifier: Programming Language :: Python :: 3
Classifier: Programming Language :: Python :: 3 :: Only
Classifier: Programming Language :: Python :: 3.7
Classifier: Programming Language :: Python :: 3.8
Classifier: Programming Language :: Python :: 3.9
Requires-Python: >=3.7
License-File: LICENSE
Requires-Dist: Babel
Requires-Dist: dill
Requires-Dist: inflect
Requires-Dist: Js2Py
Requires-Dist: lxml
Requires-Dist: pymongo
Requires-Dist: requests
Provides-Extra: testing
Requires-Dist: pytest (>=6.0) ; extra == 'testing'
Requires-Dist: pytest-cov (>=2.0) ; extra == 'testing'
Requires-Dist: mypy (>=0.910) ; extra == 'testing'
Requires-Dist: flake8 (>=3.9) ; extra == 'testing'
Requires-Dist: tox (>=3.24) ; extra == 'testing'
